<?xml version="1.0" encoding="utf-8" ?><dwsync><file name="SessionUpdateTimestampHandlerInterface.php" server="sanarsany.pdlib.org//public_html/sanarsany/" local="3729158509" remote="3736925040" Dst="-1" /><file name="index.html" server="sanarsany.pdlib.org//public_html/sanarsany/" local="3729158509" remote="3736925040" Dst="-1" /><file name="CI_Session_driver_interface.php" server="sanarsany.pdlib.org//public_html/sanarsany/" local="3729158509" remote="3736925040" Dst="-1" /><file name="PHP8SessionWrapper.php" server="sanarsany.pdlib.org//public_html/sanarsany/" local="3729158509" remote="3736925040" Dst="-1" /><file name="OldSessionWrapper.php" server="sanarsany.pdlib.org//public_html/sanarsany/" local="3729158509" remote="3736925040" Dst="-1" /><file name="Session.php" server="sanarsany.pdlib.org//public_html/sanarsany/" local="3729158509" remote="3736925040" Dst="-1" /><file name="SessionHandlerInterface.php" server="sanarsany.pdlib.org//public_html/sanarsany/" local="3729158509" remote="3736925040" Dst="-1" /><file name="Session_driver.php" server="sanarsany.pdlib.org//public_html/sanarsany/" local="3729158509" remote="3736925040" Dst="-1" /></dwsync>